odoo9_addon_document_page-9.0.2.1.0-py2.7-nspkg.pth
odoo9_addon_document_page-9.0.2.1.0.dist-info/DESCRIPTION.rst
odoo9_addon_document_page-9.0.2.1.0.dist-info/METADATA
odoo9_addon_document_page-9.0.2.1.0.dist-info/RECORD
odoo9_addon_document_page-9.0.2.1.0.dist-info/WHEEL
odoo9_addon_document_page-9.0.2.1.0.dist-info/metadata.json
odoo9_addon_document_page-9.0.2.1.0.dist-info/namespace_packages.txt
odoo9_addon_document_page-9.0.2.1.0.dist-info/top_level.txt
odoo_addons/document_page/README.rst
odoo_addons/document_page/__init__.py
odoo_addons/document_page/__openerp__.py
odoo_addons/document_page/demo/document_page.xml
odoo_addons/document_page/i18n/am.po
odoo_addons/document_page/i18n/ar.po
odoo_addons/document_page/i18n/bg.po
odoo_addons/document_page/i18n/bs.po
odoo_addons/document_page/i18n/ca.po
odoo_addons/document_page/i18n/ca_ES.po
odoo_addons/document_page/i18n/cs.po
odoo_addons/document_page/i18n/da.po
odoo_addons/document_page/i18n/da_DK.po
odoo_addons/document_page/i18n/de.po
odoo_addons/document_page/i18n/document_page.pot
odoo_addons/document_page/i18n/el.po
odoo_addons/document_page/i18n/el_GR.po
odoo_addons/document_page/i18n/en_AU.po
odoo_addons/document_page/i18n/en_GB.po
odoo_addons/document_page/i18n/es.po
odoo_addons/document_page/i18n/es_AR.po
odoo_addons/document_page/i18n/es_CL.po
odoo_addons/document_page/i18n/es_CO.po
odoo_addons/document_page/i18n/es_CR.po
odoo_addons/document_page/i18n/es_DO.po
odoo_addons/document_page/i18n/es_EC.po
odoo_addons/document_page/i18n/es_ES.po
odoo_addons/document_page/i18n/es_MX.po
odoo_addons/document_page/i18n/es_PE.po
odoo_addons/document_page/i18n/es_PY.po
odoo_addons/document_page/i18n/es_VE.po
odoo_addons/document_page/i18n/et.po
odoo_addons/document_page/i18n/eu.po
odoo_addons/document_page/i18n/fa.po
odoo_addons/document_page/i18n/fi.po
odoo_addons/document_page/i18n/fr.po
odoo_addons/document_page/i18n/fr_CA.po
odoo_addons/document_page/i18n/fr_CH.po
odoo_addons/document_page/i18n/fr_FR.po
odoo_addons/document_page/i18n/gl.po
odoo_addons/document_page/i18n/gl_ES.po
odoo_addons/document_page/i18n/gu.po
odoo_addons/document_page/i18n/he.po
odoo_addons/document_page/i18n/hi.po
odoo_addons/document_page/i18n/hr.po
odoo_addons/document_page/i18n/hr_HR.po
odoo_addons/document_page/i18n/hu.po
odoo_addons/document_page/i18n/hy.po
